cap/FunctionsSchema.json
cap/StageSchema.json
cap/VERSION
cap/WorkloadSchema.json
cap/__init__.py
cap/common.py
cap/decorators.py
cap/executor.py
cap/helper.py
cap/logutil.py
cap/main.py
cap/operation.py
cap/pyobj.py
cap/shared.py
cap/vepparser.py
cap/workload.py
cap_genomics-0.1.40.dist-info/LICENSE
cap_genomics-0.1.40.dist-info/METADATA
cap_genomics-0.1.40.dist-info/WHEEL
cap_genomics-0.1.40.dist-info/top_level.txt
cap_genomics-0.1.40.dist-info/RECORD
