Metadata-Version: 2.1
Name: cap-genomics
Version: 0.1.40
Summary: Cohort Analysis Platform
Home-page: https://github.com/ArashLab/CAP
Author: Arash Bayat
Author-email: a.bayat@garvan.org.au
License: MIT
Platform: UNKNOWN
Classifier: Programming Language :: Python :: 3
Requires-Dist: hail
Requires-Dist: munch
Requires-Dist: jsonschema
Requires-Dist: pyarrow
Requires-Dist: fastparquet
